dragonfly_ies/__init__.py
dragonfly_ies/__main__.py
dragonfly_ies/_extend_dragonfly.py
dragonfly_ies/writer.py
dragonfly_ies/cli/__init__.py
dragonfly_ies/cli/translate.py
dragonfly_ies-0.1.6.dist-info/LICENSE
dragonfly_ies-0.1.6.dist-info/METADATA
dragonfly_ies-0.1.6.dist-info/WHEEL
dragonfly_ies-0.1.6.dist-info/entry_points.txt
dragonfly_ies-0.1.6.dist-info/top_level.txt
dragonfly_ies-0.1.6.dist-info/RECORD
