Metadata-Version: 2.1
Name: dragonfly-ies
Version: 0.1.6
Summary: Dragonfly extension for export to IES-VE GEM file format
Home-page: https://github.com/ladybug-tools/dragonfly-ies
Author: Ladybug Tools
Author-email: info@ladybug.tools
License: AGPL-3.0
Platform: UNKNOWN
Classifier: Programming Language :: Python :: 3.7
Classifier: Programming Language :: Python :: Implementation :: CPython
Classifier: License :: OSI Approved :: GNU Affero General Public License v3
Classifier: Operating System :: OS Independent
License-File: LICENSE
Requires-Dist: dragonfly-core (>=1.41.7)
Requires-Dist: honeybee-ies (>=0.7.0)
